openfile/__init__.py
openfile/__main__.py
openfile/cli.py
openfile/config.py
openfile/exceptions.py
openfile/main.py
pyopenfile-0.0.3.dist-info/METADATA
pyopenfile-0.0.3.dist-info/WHEEL
pyopenfile-0.0.3.dist-info/entry_points.txt
pyopenfile-0.0.3.dist-info/top_level.txt
pyopenfile-0.0.3.dist-info/RECORD
