Metadata-Version: 2.1
Name: pyopenfile
Version: 0.0.3
Summary: UNKNOWN
Home-page: UNKNOWN
Author: greene
License: UNKNOWN
Platform: UNKNOWN
Requires-Python: >=3.8
Requires-Dist: uvicorn
Requires-Dist: fastapi
Requires-Dist: pydantic
Requires-Dist: aiofiles
Requires-Dist: python-dotenv
Requires-Dist: requests
Requires-Dist: click
Provides-Extra: dev
Requires-Dist: black ; extra == 'dev'
Requires-Dist: pytest ; extra == 'dev'
Requires-Dist: pip-tools ; extra == 'dev'
